[{"minutes": 6, "player_name": "Matt Doherty", "x": 92.0, "y": 40.805714286, "xG": 0.05, "xGOT": null, "result": "Diblok", "situation": "Permainan biasa", "shot_type": "Kaki kanan", "team": "Wolves", "h_a": "a"}, {"minutes": 14, "player_name": "Ben White", "x": 27.0199029112, "y": 29.631666665, "xG": 0.03, "xGOT": 0.12, "result": "Simpan", "situation": "Permainan biasa", "shot_type": "Kaki kanan", "team": "Arsenal", "h_a": "h"}, {"minutes": 14, "player_name": "Kai Havertz", "x": 14.9, "y": 22.247643316, "xG": 0.02, "xGOT": null, "result": "Diblok", "situation": "Permainan biasa", "shot_type": "Kaki kiri", "team": "Arsenal", "h_a": "h"}, {"minutes": 15, "player_name": "Bukayo Saka", "x": 12.3, "y": 19.7954140155, "xG": 0.02, "xGOT": 0.25, "result": "Simpan", "situation": "Permainan biasa", "shot_type": "Kaki kiri", "team": "Arsenal", "h_a": "h"}, {"minutes": 16, "player_name": "Ben White", "x": 17.7882352944, "y": 23.2985987305, "xG": 0.05, "xGOT": null, "result": "Meleset", "situation": "Permainan biasa", "shot_type": "Kaki kanan", "team": "Arsenal", "h_a": "h"}, {"minutes": 18, "player_name": "Bukayo Saka", "x": 15.2, "y": 22.3177070103, "xG": 0.03, "xGOT": 0.02, "result": "Simpan", "situation": "Permainan biasa", "shot_type": "Kaki kanan", "team": "Arsenal", "h_a": "h"}, {"minutes": 19, "player_name": "Declan Rice", "x": 14.6, "y": 37.744, "xG": 0.09, "xGOT": null, "result": "Meleset", "situation": "Set piece throw in", "shot_type": "Kaki kanan", "team": "Arsenal", "h_a": "h"}, {"minutes": 25, "player_name": "Kai Havertz", "x": 7.3333333339, "y": 33.695, "xG": 0.14, "xGOT": 0.73, "result": "Gol", "situation": "Permainan biasa", "shot_type": "Header", "team": "Arsenal", "h_a": "h"}, {"minutes": 29, "player_name": "Jean-Ricner Bellegarde", "x": 80.2325242728, "y": 37.744, "xG": 0.07, "xGOT": null, "result": "Meleset", "situation": "Tendangan bebas", "shot_type": "Kaki kanan", "team": "Wolves", "h_a": "a"}, {"minutes": 36, "player_name": "J\u00f8rgen Strand Larsen", "x": 96.7017543851, "y": 37.27875, "xG": 0.06, "xGOT": 0.06, "result": "Simpan", "situation": "Permainan biasa", "shot_type": "Header", "team": "Wolves", "h_a": "a"}, {"minutes": 37, "player_name": "Bukayo Saka", "x": 6.6578947372, "y": 30.244, "xG": 0.22, "xGOT": null, "result": "Meleset", "situation": "Permainan biasa", "shot_type": "Header", "team": "Arsenal", "h_a": "h"}, {"minutes": 40, "player_name": "Bukayo Saka", "x": 24.8800970864, "y": 30.56875, "xG": 0.05, "xGOT": null, "result": "Meleset", "situation": "Permainan biasa", "shot_type": "Kaki kiri", "team": "Arsenal", "h_a": "h"}, {"minutes": 44, "player_name": "Gabriel Martinelli", "x": 5.8859649124, "y": 45.9625477669, "xG": 0.05, "xGOT": null, "result": "Diblok", "situation": "Permainan biasa", "shot_type": "Kaki kanan", "team": "Arsenal", "h_a": "h"}, {"minutes": 50, "player_name": "Kai Havertz", "x": 11.3, "y": 39.713095239, "xG": 0.16, "xGOT": null, "result": "Meleset", "situation": "Permainan biasa", "shot_type": "Kaki kanan", "team": "Arsenal", "h_a": "h"}, {"minutes": 55, "player_name": "Gabriel", "x": 4.8362068962, "y": 30.28, "xG": 0.13, "xGOT": null, "result": "Diblok", "situation": "Dari corner", "shot_type": "Header", "team": "Arsenal", "h_a": "h"}, {"minutes": 58, "player_name": "Thomas Partey", "x": 17.6808823532, "y": 37.768, "xG": 0.06, "xGOT": null, "result": "Meleset", "situation": "Permainan biasa", "shot_type": "Kaki kiri", "team": "Arsenal", "h_a": "h"}, {"minutes": 59, "player_name": "Kai Havertz", "x": 8.5877192992, "y": 22.3877707046, "xG": 0.07, "xGOT": null, "result": "Diblok", "situation": "Permainan biasa", "shot_type": "Kaki kanan", "team": "Arsenal", "h_a": "h"}, {"minutes": 62, "player_name": "Rayan Ait Nouri", "x": 74.0383495168, "y": 27.782619047, "xG": 0.02, "xGOT": null, "result": "Meleset", "situation": "Permainan biasa", "shot_type": "Kaki kiri", "team": "Wolves", "h_a": "a"}, {"minutes": 65, "player_name": "Rodrigo Gomes", "x": 90.9, "y": 23.3686624248, "xG": 0.03, "xGOT": null, "result": "Meleset", "situation": "Permainan biasa", "shot_type": "Kaki kanan", "team": "Wolves", "h_a": "a"}, {"minutes": 68, "player_name": "Matheus Cunha", "x": 90.4, "y": 44.5612738809, "xG": 0.06, "xGOT": 0.03, "result": "Simpan", "situation": "Permainan biasa", "shot_type": "Kaki kiri", "team": "Wolves", "h_a": "a"}, {"minutes": 70, "player_name": "Martin \u00d8degaard", "x": 21.3888349512, "y": 20.2858598756, "xG": 0.02, "xGOT": 0.33, "result": "Simpan", "situation": "Taktik bola mati", "shot_type": "Kaki kiri", "team": "Arsenal", "h_a": "h"}, {"minutes": 71, "player_name": "Jurrien Timber", "x": 19.2911764712, "y": 20.7763057357, "xG": 0.02, "xGOT": null, "result": "Diblok", "situation": "Dari corner", "shot_type": "Kaki kanan", "team": "Arsenal", "h_a": "h"}, {"minutes": 74, "player_name": "Bukayo Saka", "x": 12.6, "y": 19.7954140155, "xG": 0.03, "xGOT": 0.24, "result": "Gol", "situation": "Permainan biasa", "shot_type": "Kaki kiri", "team": "Arsenal", "h_a": "h"}, {"minutes": 80, "player_name": "Kai Havertz", "x": 14.1, "y": 20.9864968186, "xG": 0.06, "xGOT": null, "result": "Diblok", "situation": "Permainan biasa", "shot_type": "Kaki kiri", "team": "Arsenal", "h_a": "h"}, {"minutes": 92, "player_name": "Matt Doherty", "x": 101.3017241382, "y": 43.7205095493, "xG": 0.03, "xGOT": null, "result": "Meleset", "situation": "Permainan biasa", "shot_type": "Header", "team": "Wolves", "h_a": "a"}, {"minutes": 94, "player_name": "Pablo Sarabia", "x": 90.9, "y": 40.46952381, "xG": 0.08, "xGOT": 0.07, "result": "Simpan", "situation": "Permainan biasa", "shot_type": "Kaki kiri", "team": "Wolves", "h_a": "a"}, {"minutes": 96, "player_name": "Daniel Podence", "x": 83.723786408, "y": 40.46952381, "xG": 0.03, "xGOT": null, "result": "Meleset", "situation": "Permainan biasa", "shot_type": "Kaki kiri", "team": "Wolves", "h_a": "a"}]